README.rst
setup.cfg
setup.py
sasx/__init__.py
sasx/code.py
sasx/magic.py
sasx/parse.py
sasx.egg-info/PKG-INFO
sasx.egg-info/SOURCES.txt
sasx.egg-info/dependency_links.txt
sasx.egg-info/requires.txt
sasx.egg-info/top_level.txt